{"reportNo":3,"time":"Generated on the 4th of january 2025 at 00:41","matureCards":[{"reportNo":3,"matureCardCount":3200},{"reportNo":2,"matureCardCount":3200},{"reportNo":1,"matureCardCount":3200}],"retentionRate":{"current":76.77966101694915,"delta":0},"totalReviews":{"current":167,"delta":0},"AnkiStreak":{"current":0,"delta":0},"AnkiData":[{"reportNo":3,"value":0},{"reportNo":2,"value":0},{"reportNo":1,"value":167}],"ImmersionTime":{"current":3,"delta":0},"AverageImmersionTime":{"current":2302.1666666666665,"delta":-2302.1666666666665},"MonthlyImmersion":26960,"BestImmersion":{"current":0,"delta":0},"ImmersionLog":[],"ImmersionData":[{"reportNo":3,"value":0},{"reportNo":2,"value":0},{"reportNo":1,"value":13813}],"ImmersionStreak":{"current":0,"delta":0},"ImmersionScore":0,"AnkiScore":0,"TotalScore":0,"lastDaysPoints":[13980,13980,13980]}